srtm/__init__.py
srtm/base_coordinates.py
srtm/exceptions.py
srtm/height_map_collection.py
srtm/height_maps.py
srtm/utilities.py
python_srtm-0.6.0.dist-info/METADATA
python_srtm-0.6.0.dist-info/WHEEL
python_srtm-0.6.0.dist-info/RECORD
