Metadata-Version: 2.1
Name: python-srtm
Version: 0.6.0
Summary: 
Home-page: https://github.com/adamcharnock/python-srtm
License: MIT
Keywords: nasa,geospatial,altitude,elevation-profile
Author: Adam Charnock
Author-email: adam@adamcharnock.com
Requires-Python: >=3.8,<4.0
Classifier: License :: OSI Approved :: MIT License
Classifier: Programming Language :: Python :: 3
Classifier: Programming Language :: Python :: 3.8
Classifier: Programming Language :: Python :: 3.9
Classifier: Programming Language :: Python :: 3.10
Classifier: Programming Language :: Python :: 3.11
Classifier: Programming Language :: Python :: 3.12
Project-URL: Repository, https://github.com/adamcharnock/python-srtm
